{
  "version": "0.1.12",
  "react_modules": [
    {
      "name": "admin",
      "buildPath": "modules/admin/build/",
      "classPath": "src/Admin/",
      "className": "SettingsPage.php",
      "versions": {
        "previous": {
          "assets": {
            "css": "main.073c9b0a.css",
            "js": "main.5290b9e7.js"
          }
        },
        "current": {
          "assets": {
            "css": "main.0000000.css",
            "js": "main.0000000.js"
          }
        }
      }
    }
  ]
}
